aladdin/EMA.py
aladdin/__init__.py
aladdin/check_accuracy.py
aladdin/find_optimal_workers.py
aladdin-0.0.3.dist-info/LICENSE
aladdin-0.0.3.dist-info/METADATA
aladdin-0.0.3.dist-info/WHEEL
aladdin-0.0.3.dist-info/top_level.txt
aladdin-0.0.3.dist-info/RECORD
