Metadata-Version: 2.1
Name: aladdin
Version: 0.0.3
Summary: Useful deep learning functions
Home-page: https://github.com/aladdinpersson/DL-Utils
Author: Aladdin Persson
Author-email: aladdin.persson@hotmail.com
License: MIT
Platform: UNKNOWN
Requires-Dist: torch
